[
  {
    "name": "IMG_20211117_204907.jpg",
    "url": "https://drive.google.com/thumbnail?id=1GEGXhbczj5Pd2IiKIc9aEFToq10T5If4&sz=w2000",
    "date": "2026-05-10T22:41:37.636Z",
    "title": "IMG_20211117_204907.jpg",
    "text": "Recuerdo de Copito 🤍"
  },
  {
    "name": "IMG_20211117_204903.jpg",
    "url": "https://drive.google.com/thumbnail?id=1zR-09MH1SUSk673EElib_8VcIzcbXC80&sz=w2000",
    "date": "2026-05-10T23:12:27.743Z",
    "title": "IMG_20211117_204903.jpg",
    "text": "Recuerdo de Copito 🤍"
  },
  {
    "name": "IMG_20211117_204909.jpg",
    "url": "https://drive.google.com/thumbnail?id=1jOQjwNdGmpAaIc7JCd7GSh9Yuym2fJTC&sz=w2000",
    "date": "2026-05-10T22:42:01.064Z",
    "title": "IMG_20211117_204909.jpg",
    "text": "Recuerdo de Copito 🤍"
  },
  {
    "name": "IMG_20211117_204904.jpg",
    "url": "https://drive.google.com/thumbnail?id=1kzIrn-NScVVrVNX3USYNA_YY4_Oh6JZE&sz=w2000",
    "date": "2026-05-10T22:42:39.765Z",
    "title": "IMG_20211117_204904.jpg",
    "text": "Recuerdo de Copito 🤍"
  },
  {
    "name": "IMG_20260104_115720.jpg",
    "url": "https://drive.google.com/thumbnail?id=141M7fZrzE0XBsJCcV6CRBtTC5u_yLM8j&sz=w2000",
    "date": "2026-05-10T22:43:02.019Z",
    "title": "IMG_20260104_115720.jpg",
    "text": "Recuerdo de Copito 🤍"
  },
  {
    "name": "20220804_205140.jpg",
    "url": "https://drive.google.com/thumbnail?id=1LznPUQvGxnj2tlLMkGU6YzYSw3ZWGgQ_&sz=w2000",
    "date": "2026-05-10T22:42:15.930Z",
    "title": "20220804_205140.jpg",
    "text": "Recuerdo de Copito 🤍"
  },
  {
    "name": "20220804_205147.jpg",
    "url": "https://drive.google.com/thumbnail?id=1K64brPwp52QJ9kzaanLWiFKfF2-P3lTI&sz=w2000",
    "date": "2026-05-10T22:42:27.504Z",
    "title": "20220804_205147.jpg",
    "text": "Recuerdo de Copito 🤍"
  },
  {
    "name": "IMG_20211127_194000.jpg",
    "url": "https://drive.google.com/thumbnail?id=1rdkTfNTLq2sMOloEvKWYo5pnlXIkJi1s&sz=w2000",
    "date": "2026-05-10T22:42:52.107Z",
    "title": "IMG_20211127_194000.jpg",
    "text": "Recuerdo de Copito 🤍"
  },
  {
    "name": "IMG_20230116_205919.jpg",
    "url": "https://drive.google.com/thumbnail?id=1uW5mE_LAHBBLs2u7zJGMd-OhKm62j2ec&sz=w2000",
    "date": "2026-05-10T22:49:06.009Z",
    "title": "IMG_20230116_205919.jpg",
    "text": "Recuerdo de Copito 🤍"
  },
  {
    "name": "AGC_20250127_134813035.jpg",
    "url": "https://drive.google.com/thumbnail?id=13alzgvDc4nudHWRfuT6UfxcJtR-ZHeZf&sz=w2000",
    "date": "2026-05-10T22:48:19.660Z",
    "title": "AGC_20250127_134813035.jpg",
    "text": "Recuerdo de Copito 🤍"
  },
  {
    "name": "AGC_20241015_141636833.jpg",
    "url": "https://drive.google.com/thumbnail?id=1TfKQ95XV_h_OQ4TObizjVoqRXboU3Niv&sz=w2000",
    "date": "2026-05-10T22:47:19.741Z",
    "title": "AGC_20241015_141636833.jpg",
    "text": "Recuerdo de Copito 🤍"
  },
  {
    "name": "AGC_20250115_211324701.jpg",
    "url": "https://drive.google.com/thumbnail?id=180gzQ9A0Ro9zxjhjNNSdvaHGAp6JiVqA&sz=w2000",
    "date": "2026-05-10T22:48:03.110Z",
    "title": "AGC_20250115_211324701.jpg",
    "text": "Recuerdo de Copito 🤍"
  },
  {
    "name": "IMG_20221224_141356.jpg",
    "url": "https://drive.google.com/thumbnail?id=17DufCpKlvqdDreUZBuHlMkoElO-4WKuA&sz=w2000",
    "date": "2026-05-10T22:48:44.408Z",
    "title": "IMG_20221224_141356.jpg",
    "text": "Recuerdo de Copito 🤍"
  },
  {
    "name": "AGC_20240906_135330485.jpg",
    "url": "https://drive.google.com/thumbnail?id=1MuPSWttO5LY81opjg6oycTkiBK1D_MeD&sz=w2000",
    "date": "2026-05-10T22:41:15.958Z",
    "title": "AGC_20240906_135330485.jpg",
    "text": "Recuerdo de Copito 🤍"
  },
  {
    "name": "IMG_20221224_141354.jpg",
    "url": "https://drive.google.com/thumbnail?id=1jCR-kwptFN8va5iaijEMbQwFIk90c_Y4&sz=w2000",
    "date": "2026-05-10T22:48:38.744Z",
    "title": "IMG_20221224_141354.jpg",
    "text": "Recuerdo de Copito 🤍"
  },
  {
    "name": "AGC_20250127_141722330.jpg",
    "url": "https://drive.google.com/thumbnail?id=1oaRfbc6kvahLWgqDzsxuRH7UFJwg0uDS&sz=w2000",
    "date": "2026-05-10T22:48:23.897Z",
    "title": "AGC_20250127_141722330.jpg",
    "text": "Recuerdo de Copito 🤍"
  },
  {
    "name": "IMG_20230119_140531.jpg",
    "url": "https://drive.google.com/thumbnail?id=1oGObh8Fc42E-byqDE93lMlI1013_jTpW&sz=w2000",
    "date": "2026-05-10T22:49:23.889Z",
    "title": "IMG_20230119_140531.jpg",
    "text": "Recuerdo de Copito 🤍"
  },
  {
    "name": "IMG_20230116_205921.jpg",
    "url": "https://drive.google.com/thumbnail?id=1Rg5jFn6N1kiSme7eDjsZbziW-k0m4-Z5&sz=w2000",
    "date": "2026-05-10T22:49:10.894Z",
    "title": "IMG_20230116_205921.jpg",
    "text": "Recuerdo de Copito 🤍"
  },
  {
    "name": "AGC_20250116_163052681.jpg",
    "url": "https://drive.google.com/thumbnail?id=15rkzU-kC7-4C0SkF6PR70qNXGJhXHWPB&sz=w2000",
    "date": "2026-05-10T22:48:11.217Z",
    "title": "AGC_20250116_163052681.jpg",
    "text": "Recuerdo de Copito 🤍"
  },
  {
    "name": "AGC_20241019_151854377.jpg",
    "url": "https://drive.google.com/thumbnail?id=1qDQ8nNvO12yk3ICJBbBOxnPiAUYy4EWh&sz=w2000",
    "date": "2026-05-10T22:47:31.384Z",
    "title": "AGC_20241019_151854377.jpg",
    "text": "Recuerdo de Copito 🤍"
  },
  {
    "name": "IMG_20221224_141405.jpg",
    "url": "https://drive.google.com/thumbnail?id=1WB9aLlW04yRPthSbWqxk2LRie_IPyVff&sz=w2000",
    "date": "2026-05-10T22:48:48.382Z",
    "title": "IMG_20221224_141405.jpg",
    "text": "Recuerdo de Copito 🤍"
  },
  {
    "name": "AGC_20240830_152722783.jpg",
    "url": "https://drive.google.com/thumbnail?id=1Ushe2uDlFJ8_XUHnrZtIVmBuXPNHKZat&sz=w2000",
    "date": "2026-05-10T22:41:15.180Z",
    "title": "AGC_20240830_152722783.jpg",
    "text": "Recuerdo de Copito 🤍"
  },
  {
    "name": "IMG_20230119_140518.jpg",
    "url": "https://drive.google.com/thumbnail?id=1ATt9QSxZwNkRxgXEOdT5xE3ir-90JBm1&sz=w2000",
    "date": "2026-05-10T22:49:19.393Z",
    "title": "IMG_20230119_140518.jpg",
    "text": "Recuerdo de Copito 🤍"
  },
  {
    "name": "20141115_131451.jpg",
    "url": "https://drive.google.com/thumbnail?id=1hC8ncECjmrVfXgUIddVytkibagQjMyR-&sz=w2000",
    "date": "2026-05-10T22:46:48.104Z",
    "title": "20141115_131451.jpg",
    "text": "Recuerdo de Copito 🤍"
  },
  {
    "name": "20141116_150722.jpg",
    "url": "https://drive.google.com/thumbnail?id=1ea4t1Ev8QD4a9PkcA6iCOD1y0KXLv7cf&sz=w2000",
    "date": "2026-05-10T22:46:55.462Z",
    "title": "20141116_150722.jpg",
    "text": "Recuerdo de Copito 🤍"
  },
  {
    "name": "20141115_131441.jpg",
    "url": "https://drive.google.com/thumbnail?id=17rsEHS8KAcN1ruEBbdtPR97psFrnG9iw&sz=w2000",
    "date": "2026-05-10T22:46:39.953Z",
    "title": "20141115_131441.jpg",
    "text": "Recuerdo de Copito 🤍"
  },
  {
    "name": "AGC_20250121_183631435.jpg",
    "url": "https://drive.google.com/thumbnail?id=1JctISSfJ3OWTPKVRMZ1nbAiWE_qg5Jh1&sz=w2000",
    "date": "2026-05-10T22:48:15.583Z",
    "title": "AGC_20250121_183631435.jpg",
    "text": "Recuerdo de Copito 🤍"
  },
  {
    "name": "IMG_20230116_205910.jpg",
    "url": "https://drive.google.com/thumbnail?id=1SqCOzwib32nZ1i4M1pghNI05kOhesUmt&sz=w2000",
    "date": "2026-05-10T22:49:01.328Z",
    "title": "IMG_20230116_205910.jpg",
    "text": "Recuerdo de Copito 🤍"
  },
  {
    "name": "IMG_20221222_154018.jpg",
    "url": "https://drive.google.com/thumbnail?id=1z0SNudEgDISOBhCH9Z6Pl3DsTNiABAXA&sz=w2000",
    "date": "2026-05-10T22:48:32.908Z",
    "title": "IMG_20221222_154018.jpg",
    "text": "Recuerdo de Copito 🤍"
  },
  {
    "name": "AGC_20250109_215131282.jpg",
    "url": "https://drive.google.com/thumbnail?id=1thDT81WSo2LBgHK8D1SN4yQEhd1pFqgd&sz=w2000",
    "date": "2026-05-10T22:47:59.925Z",
    "title": "AGC_20250109_215131282.jpg",
    "text": "Recuerdo de Copito 🤍"
  },
  {
    "name": "20141115_131444.jpg",
    "url": "https://drive.google.com/thumbnail?id=1WxI7FcgpSneO55Dpt4-AaiSWxxoo6iV_&sz=w2000",
    "date": "2026-05-10T22:46:43.991Z",
    "title": "20141115_131444.jpg",
    "text": "Recuerdo de Copito 🤍"
  },
  {
    "name": "20141116_140857.jpg",
    "url": "https://drive.google.com/thumbnail?id=1TeJCk4eJrgGGezYqXbW1FxmSrYBGKCTs&sz=w2000",
    "date": "2026-05-10T22:46:51.782Z",
    "title": "20141116_140857.jpg",
    "text": "Recuerdo de Copito 🤍"
  },
  {
    "name": "AGC_20240828_134218460.jpg",
    "url": "https://drive.google.com/thumbnail?id=1S0JlX7y8oCGvgqpQ8aTXqaNnnO5QGoZy&sz=w2000",
    "date": "2026-05-10T22:47:07.241Z",
    "title": "AGC_20240828_134218460.jpg",
    "text": "Recuerdo de Copito 🤍"
  },
  {
    "name": "AGC_20240819_135732796.jpg",
    "url": "https://drive.google.com/thumbnail?id=1by8UkRS5b_hK0l_sGBfSfad40cnRU92_&sz=w2000",
    "date": "2026-05-10T22:47:03.357Z",
    "title": "AGC_20240819_135732796.jpg",
    "text": "Recuerdo de Copito 🤍"
  },
  {
    "name": "AGC_20240828_134346273.jpg",
    "url": "https://drive.google.com/thumbnail?id=1fRQdvCARVMuYZn9rpN_enjJDanhGW8xY&sz=w2000",
    "date": "2026-05-10T22:47:12.059Z",
    "title": "AGC_20240828_134346273.jpg",
    "text": "Recuerdo de Copito 🤍"
  },
  {
    "name": "AGC_20241024_144846799.jpg",
    "url": "https://drive.google.com/thumbnail?id=1YnAHpBdwMRSnCoSqhEda9tGzBsWuqBGW&sz=w2000",
    "date": "2026-05-10T22:47:39.414Z",
    "title": "AGC_20241024_144846799.jpg",
    "text": "Recuerdo de Copito 🤍"
  },
  {
    "name": "AGC_20241025_131539185.jpg",
    "url": "https://drive.google.com/thumbnail?id=1KsB8URMd0njdxQG5P2d-Wy-HpYNfLJ7q&sz=w2000",
    "date": "2026-05-10T22:47:56.231Z",
    "title": "AGC_20241025_131539185.jpg",
    "text": "Recuerdo de Copito 🤍"
  },
  {
    "name": "IMG_20221228_174513.jpg",
    "url": "https://drive.google.com/thumbnail?id=1LA6gL88Jw-wZhbv68hNePspTIXRJoeGZ&sz=w2000",
    "date": "2026-05-10T22:48:52.522Z",
    "title": "IMG_20221228_174513.jpg",
    "text": "Recuerdo de Copito 🤍"
  },
  {
    "name": "AGC_20241019_151825208.jpg",
    "url": "https://drive.google.com/thumbnail?id=1MzkMg-yucf5dxjhw8oOBd42Ss9z06LgS&sz=w2000",
    "date": "2026-05-10T22:47:23.443Z",
    "title": "AGC_20241019_151825208.jpg",
    "text": "Recuerdo de Copito 🤍"
  },
  {
    "name": "IMG_20230309_211739.jpg",
    "url": "https://drive.google.com/thumbnail?id=1CoooDhSESnIsi5mTaO4fTjuZtcMN0gmP&sz=w2000",
    "date": "2026-05-10T22:49:33.529Z",
    "title": "IMG_20230309_211739.jpg",
    "text": "Recuerdo de Copito 🤍"
  },
  {
    "name": "AGC_20240815_145102323.jpg",
    "url": "https://drive.google.com/thumbnail?id=1vAdB2qeqzveSL-Qy7z_M1gOOaPfXv1wE&sz=w2000",
    "date": "2026-05-10T22:41:15.195Z",
    "title": "AGC_20240815_145102323.jpg",
    "text": "Recuerdo de Copito 🤍"
  },
  {
    "name": "IMG_20230119_124915.jpg",
    "url": "https://drive.google.com/thumbnail?id=1tqBsjMHy-eMENf1GYzGMFlrPLzpuU3Na&sz=w2000",
    "date": "2026-05-10T22:49:15.142Z",
    "title": "IMG_20230119_124915.jpg",
    "text": "Recuerdo de Copito 🤍"
  },
  {
    "name": "IMG_20221230_155009.jpg",
    "url": "https://drive.google.com/thumbnail?id=1Os0VDw-LipRzyZDT6rvUCxzL5lFJJi1m&sz=w2000",
    "date": "2026-05-10T22:48:56.720Z",
    "title": "IMG_20221230_155009.jpg",
    "text": "Recuerdo de Copito 🤍"
  },
  {
    "name": "AGC_20240906_135439988.jpg",
    "url": "https://drive.google.com/thumbnail?id=1fwPHcd5LMBLDp4PBPgZ5lG2FDlDOI-MK&sz=w2000",
    "date": "2026-05-10T22:41:11.783Z",
    "title": "AGC_20240906_135439988.jpg",
    "text": "Recuerdo de Copito 🤍"
  },
  {
    "name": "AGC_20241019_151846481.jpg",
    "url": "https://drive.google.com/thumbnail?id=1T_isRE97UfTezcTOgPpk9nAAB3gXIWcc&sz=w2000",
    "date": "2026-05-10T22:47:27.313Z",
    "title": "AGC_20241019_151846481.jpg",
    "text": "Recuerdo de Copito 🤍"
  },
  {
    "name": "AGC_20250115_211352171.jpg",
    "url": "https://drive.google.com/thumbnail?id=1q3ecvEBZkYiPGMgR9PjonV8v858xM7gh&sz=w2000",
    "date": "2026-05-10T22:48:06.813Z",
    "title": "AGC_20250115_211352171.jpg",
    "text": "Recuerdo de Copito 🤍"
  },
  {
    "name": "AGC_20241025_131451916.jpg",
    "url": "https://drive.google.com/thumbnail?id=1sBFNgfgNZggcbQQ1DNo8wb4P-xj3k3--&sz=w2000",
    "date": "2026-05-10T22:47:43.781Z",
    "title": "AGC_20241025_131451916.jpg",
    "text": "Recuerdo de Copito 🤍"
  },
  {
    "name": "IMG_20230119_140532.jpg",
    "url": "https://drive.google.com/thumbnail?id=1dzh2_OeG_khNWlbWFefUfTDQpHTLnPyW&sz=w2000",
    "date": "2026-05-10T22:49:28.490Z",
    "title": "IMG_20230119_140532.jpg",
    "text": "Recuerdo de Copito 🤍"
  },
  {
    "name": "AGC_20240916_143443501.jpg",
    "url": "https://drive.google.com/thumbnail?id=1FnVSQbifVUh3sV7tN-Mafi1s5gsprRjm&sz=w2000",
    "date": "2026-05-10T22:47:15.852Z",
    "title": "AGC_20240916_143443501.jpg",
    "text": "Recuerdo de Copito 🤍"
  },
  {
    "name": "AGC_20240819_135959114.jpg",
    "url": "https://drive.google.com/thumbnail?id=15tjK1SUwmxSyLZPDgMJBsJwztfH8ssAS&sz=w2000",
    "date": "2026-05-10T22:41:15.884Z",
    "title": "AGC_20240819_135959114.jpg",
    "text": "Recuerdo de Copito 🤍"
  },
  {
    "name": "AGC_20241025_131528535.jpg",
    "url": "https://drive.google.com/thumbnail?id=1uWWqG0ScNW3v1HUqcE03ME_-AKvZgr1u&sz=w2000",
    "date": "2026-05-10T22:47:47.779Z",
    "title": "AGC_20241025_131528535.jpg",
    "text": "Recuerdo de Copito 🤍"
  },
  {
    "name": "AGC_20240815_121933300.jpg",
    "url": "https://drive.google.com/thumbnail?id=1tnuC_BTT1HLdw9ISIZE6Gf7i5xcfdfgH&sz=w2000",
    "date": "2026-05-10T22:46:59.076Z",
    "title": "AGC_20240815_121933300.jpg",
    "text": "Recuerdo de Copito 🤍"
  },
  {
    "name": "AGC_20241025_131536087.jpg",
    "url": "https://drive.google.com/thumbnail?id=1Ka2vpVs_v_1FJ3lLWxXQbDoeJlhsHFMU&sz=w2000",
    "date": "2026-05-10T22:47:52.283Z",
    "title": "AGC_20241025_131536087.jpg",
    "text": "Recuerdo de Copito 🤍"
  },
  {
    "name": "AGC_20240830_152734638.jpg",
    "url": "https://drive.google.com/thumbnail?id=1DrErm6eh9udViZy3KRHbj1Wv-HXNHk0Z&sz=w2000",
    "date": "2026-05-10T22:41:15.821Z",
    "title": "AGC_20240830_152734638.jpg",
    "text": "Recuerdo de Copito 🤍"
  },
  {
    "name": "AGC_20241019_151916516.jpg",
    "url": "https://drive.google.com/thumbnail?id=1T0Jze7FVQUKqN9StatrQcCmdNPwPIc4i&sz=w2000",
    "date": "2026-05-10T22:47:35.341Z",
    "title": "AGC_20241019_151916516.jpg",
    "text": "Recuerdo de Copito 🤍"
  },
  {
    "name": "IMG_20221222_154012.jpg",
    "url": "https://drive.google.com/thumbnail?id=1Jv0M-uxxn-7zd7lkjZgoN6m9mXimX0Xv&sz=w2000",
    "date": "2026-05-10T22:48:28.549Z",
    "title": "IMG_20221222_154012.jpg",
    "text": "Recuerdo de Copito 🤍"
  },
  {
    "name": "IMG_20160524_204858.jpg",
    "url": "https://drive.google.com/thumbnail?id=1zwScm511eUzVWXC7Apo6rWHd_F2uolWg&sz=w2000",
    "date": "2026-05-10T22:41:16.010Z",
    "title": "IMG_20160524_204858.jpg",
    "text": "Recuerdo de Copito 🤍"
  },
  {
    "name": "IMG_20160524_204904.jpg",
    "url": "https://drive.google.com/thumbnail?id=1G6QpKZC99mRlLPvmLRxSFjagVeEz0Cay&sz=w2000",
    "date": "2026-05-10T22:52:10.130Z",
    "title": "IMG_20160524_204904.jpg",
    "text": "Recuerdo de Copito 🤍"
  },
  {
    "name": "IMG-20160114-WA0000.jpg",
    "url": "https://drive.google.com/thumbnail?id=1PayjUZGmaw5byJ125O87HxGKyKqAk1Es&sz=w2000",
    "date": "2026-05-10T22:41:29.051Z",
    "title": "IMG-20160114-WA0000.jpg",
    "text": "Recuerdo de Copito 🤍"
  },
  {
    "name": "IMG_20171205_150717.jpg",
    "url": "https://drive.google.com/thumbnail?id=1t7Oo7xsJdMH8uItCuyct09QqJZO-PhiL&sz=w2000",
    "date": "2026-05-10T22:52:30.727Z",
    "title": "IMG_20171205_150717.jpg",
    "text": "Recuerdo de Copito 🤍"
  },
  {
    "name": "IMG_20180716_211232.jpg",
    "url": "https://drive.google.com/thumbnail?id=10RYwYyTBJXvWnSl27i-hZKaOm0Sg3Y0d&sz=w2000",
    "date": "2026-05-10T22:41:30.421Z",
    "title": "IMG_20180716_211232.jpg",
    "text": "Recuerdo de Copito 🤍"
  },
  {
    "name": "IMG_20161231_212437.jpg",
    "url": "https://drive.google.com/thumbnail?id=1aTwECJhuyxjO1e1tpR8VRRhgNxZIpV3n&sz=w2000",
    "date": "2026-05-10T22:52:17.603Z",
    "title": "IMG_20161231_212437.jpg",
    "text": "Recuerdo de Copito 🤍"
  },
  {
    "name": "IMG_20201029_000513_1.jpg",
    "url": "https://drive.google.com/thumbnail?id=1JSONdt-gcPs9Fr3-hb4Uv7Yr3Pvm_C1z&sz=w2000",
    "date": "2026-05-10T22:52:41.837Z",
    "title": "IMG_20201029_000513_1.jpg",
    "text": "Recuerdo de Copito 🤍"
  },
  {
    "name": "IMG_20160629_192443.jpg",
    "url": "https://drive.google.com/thumbnail?id=1MyqlrUt9-zJO1Loo39j4pEAvpdF-j8yO&sz=w2000",
    "date": "2026-05-10T22:41:24.203Z",
    "title": "IMG_20160629_192443.jpg",
    "text": "Recuerdo de Copito 🤍"
  },
  {
    "name": "AGC_20250127_141747667.jpg",
    "url": "https://drive.google.com/thumbnail?id=1ou5Vr131Pt8O8kTxgNk75r1D6TUqaMkG&sz=w2000",
    "date": "2026-05-10T22:51:19.619Z",
    "title": "AGC_20250127_141747667.jpg",
    "text": "Recuerdo de Copito 🤍"
  },
  {
    "name": "IMG_20160524_204858_01.jpg",
    "url": "https://drive.google.com/thumbnail?id=1yVLR-WYB7VUz4pP-w5Rcb1bZPA2E15BQ&sz=w2000",
    "date": "2026-05-10T22:41:24.598Z",
    "title": "IMG_20160524_204858_01.jpg",
    "text": "Recuerdo de Copito 🤍"
  },
  {
    "name": "IMG_20160629_192437.jpg",
    "url": "https://drive.google.com/thumbnail?id=1gv8fVbDPcWVd8WGmdmkt8EgyVqiDDndA&sz=w2000",
    "date": "2026-05-10T22:41:23.631Z",
    "title": "IMG_20160629_192437.jpg",
    "text": "Recuerdo de Copito 🤍"
  },
  {
    "name": "IMG_20171205_150732_Bokeh.jpg",
    "url": "https://drive.google.com/thumbnail?id=1SPrv3guQR47wKhrCWcdAeMm68URbnkC3&sz=w2000",
    "date": "2026-05-10T22:52:34.295Z",
    "title": "IMG_20171205_150732_Bokeh.jpg",
    "text": "Recuerdo de Copito 🤍"
  },
  {
    "name": "IMG_20180716_211227.jpg",
    "url": "https://drive.google.com/thumbnail?id=1P_fcxzSK8qLm2TrF0QtO5vDq3S6_UERi&sz=w2000",
    "date": "2026-05-10T22:41:24.087Z",
    "title": "IMG_20180716_211227.jpg",
    "text": "Recuerdo de Copito 🤍"
  },
  {
    "name": "IMG_20161231_212431_1.jpg",
    "url": "https://drive.google.com/thumbnail?id=1K3mY9nHifdeP5PxxaoQACX8u-YiznAKS&sz=w2000",
    "date": "2026-05-10T22:52:13.644Z",
    "title": "IMG_20161231_212431_1.jpg",
    "text": "Recuerdo de Copito 🤍"
  },
  {
    "name": "IMG_20170626_192142.jpg",
    "url": "https://drive.google.com/thumbnail?id=1XGIyKHd5Wm3ly-f23uHpW6CpHAAIjdyX&sz=w2000",
    "date": "2026-05-10T22:41:22.449Z",
    "title": "IMG_20170626_192142.jpg",
    "text": "Recuerdo de Copito 🤍"
  },
  {
    "name": "AGC_20250127_134856655.jpg",
    "url": "https://drive.google.com/thumbnail?id=1QDYdCDpqXsI_ip5jLsDSA9159yPpFiTa&sz=w2000",
    "date": "2026-05-10T22:41:14.923Z",
    "title": "AGC_20250127_134856655.jpg",
    "text": "Recuerdo de Copito 🤍"
  },
  {
    "name": "DSC01458.JPG",
    "url": "https://drive.google.com/thumbnail?id=1v7R_hr42FQI7iUYuAIBGMQIagphDTxN6&sz=w2000",
    "date": "2026-05-10T22:51:39.169Z",
    "title": "DSC01458.JPG",
    "text": "Recuerdo de Copito 🤍"
  },
  {
    "name": "DSC01082.JPG",
    "url": "https://drive.google.com/thumbnail?id=1TL4wF00zItskWTzS1BVk4qHHXs3R2Ti_&sz=w2000",
    "date": "2026-05-10T22:51:33.542Z",
    "title": "DSC01082.JPG",
    "text": "Recuerdo de Copito 🤍"
  },
  {
    "name": "IMG_20170303_215719(1).jpg",
    "url": "https://drive.google.com/thumbnail?id=1MQ0mCGI9-ayhY5xwY_hu45ks_c1o7zpf&sz=w2000",
    "date": "2026-05-10T22:41:21.340Z",
    "title": "IMG_20170303_215719(1).jpg",
    "text": "Recuerdo de Copito 🤍"
  },
  {
    "name": "AGC_20250127_134849816.jpg",
    "url": "https://drive.google.com/thumbnail?id=13-xWAv6A4fE39fNyEszGWFeBLUDTGiu_&sz=w2000",
    "date": "2026-05-10T22:41:14.455Z",
    "title": "AGC_20250127_134849816.jpg",
    "text": "Recuerdo de Copito 🤍"
  },
  {
    "name": "IMG_20161231_212502.jpg",
    "url": "https://drive.google.com/thumbnail?id=1IbRj9OmqTByeDjUXYka-1TQFgQXguGNX&sz=w2000",
    "date": "2026-05-10T22:52:26.861Z",
    "title": "IMG_20161231_212502.jpg",
    "text": "Recuerdo de Copito 🤍"
  },
  {
    "name": "AGC_20250127_134835643.jpg",
    "url": "https://drive.google.com/thumbnail?id=1GraY4YqHZapVosY4iDz_pBxmeR5PNhKg&sz=w2000",
    "date": "2026-05-10T22:41:13.780Z",
    "title": "AGC_20250127_134835643.jpg",
    "text": "Recuerdo de Copito 🤍"
  },
  {
    "name": "IMG-20141025-WA0000.jpg",
    "url": "https://drive.google.com/thumbnail?id=1wao3OmOVEwikFJdl2my3PyjxtqhiIGNm&sz=w2000",
    "date": "2026-05-10T22:41:28.469Z",
    "title": "IMG-20141025-WA0000.jpg",
    "text": "Recuerdo de Copito 🤍"
  },
  {
    "name": "IMG_20160524_204901.jpg",
    "url": "https://drive.google.com/thumbnail?id=1NJSWPItcedCoEmcCRM2Q3gSu6kwwPIUk&sz=w2000",
    "date": "2026-05-10T22:41:24.923Z",
    "title": "IMG_20160524_204901.jpg",
    "text": "Recuerdo de Copito 🤍"
  },
  {
    "name": "DSC00607.JPG",
    "url": "https://drive.google.com/thumbnail?id=1eN5wXHrmRCLD37SnDuUvagiSIycfYCpA&sz=w2000",
    "date": "2026-05-10T22:51:26.752Z",
    "title": "DSC00607.JPG",
    "text": "Recuerdo de Copito 🤍"
  },
  {
    "name": "20220331_090116.jpg",
    "url": "https://drive.google.com/thumbnail?id=1izmMjwMdRazr9zBcSyg6VeboLDhhF6Ct&sz=w2000",
    "date": "2026-05-10T22:51:12.497Z",
    "title": "20220331_090116.jpg",
    "text": "Recuerdo de Copito 🤍"
  },
  {
    "name": "DSC01459.JPG",
    "url": "https://drive.google.com/thumbnail?id=1RKAfKBovz4hnTqXfGnEfLkoUSe_5Kpkd&sz=w2000",
    "date": "2026-05-10T22:51:45.216Z",
    "title": "DSC01459.JPG",
    "text": "Recuerdo de Copito 🤍"
  },
  {
    "name": "IMG_20190331_155642.jpg",
    "url": "https://drive.google.com/thumbnail?id=1O2Wcgd-tyvCcYbgvrEmkmf4iPC9K3jPX&sz=w2000",
    "date": "2026-05-10T22:41:29.858Z",
    "title": "IMG_20190331_155642.jpg",
    "text": "Recuerdo de Copito 🤍"
  },
  {
    "name": "AGC_20250127_141804592.jpg",
    "url": "https://drive.google.com/thumbnail?id=1Htg_w4-VQ3XfMDh45JdJjYZOrJnmEa9m&sz=w2000",
    "date": "2026-05-10T22:51:23.511Z",
    "title": "AGC_20250127_141804592.jpg",
    "text": "Recuerdo de Copito 🤍"
  },
  {
    "name": "DSC00861.JPG",
    "url": "https://drive.google.com/thumbnail?id=123auSbJr2dZsG7whcFCK83rhaKlC-6iB&sz=w2000",
    "date": "2026-05-10T22:41:12.875Z",
    "title": "DSC00861.JPG",
    "text": "Recuerdo de Copito 🤍"
  },
  {
    "name": "IMG_20160524_204854.jpg",
    "url": "https://drive.google.com/thumbnail?id=1ZsMZGiYR0ErPC64tA6lYBtrnkXrZdFfa&sz=w2000",
    "date": "2026-05-10T22:41:16.093Z",
    "title": "IMG_20160524_204854.jpg",
    "text": "Recuerdo de Copito 🤍"
  },
  {
    "name": "IMG-20141028-WA0000.jpg",
    "url": "https://drive.google.com/thumbnail?id=1bTmNrgHEEJbY-A879wGZQbvrb6ApvMNU&sz=w2000",
    "date": "2026-05-10T22:41:28.345Z",
    "title": "IMG-20141028-WA0000.jpg",
    "text": "Recuerdo de Copito 🤍"
  },
  {
    "name": "IMG_20170303_215708-COLLAGE.jpg",
    "url": "https://drive.google.com/thumbnail?id=1MzOMm_sUgPEpIghcRNGIr8NlX5sY1tcH&sz=w2000",
    "date": "2026-05-10T22:41:23.037Z",
    "title": "IMG_20170303_215708-COLLAGE.jpg",
    "text": "Recuerdo de Copito 🤍"
  },
  {
    "name": "DSC01461.JPG",
    "url": "https://drive.google.com/thumbnail?id=17ADYN_JUP2WKxiyPlHhLJ3LUYONSyU69&sz=w2000",
    "date": "2026-05-10T22:51:51.227Z",
    "title": "DSC01461.JPG",
    "text": "Recuerdo de Copito 🤍"
  },
  {
    "name": "DSC00474.JPG",
    "url": "https://drive.google.com/thumbnail?id=1VGl5Ke34A9bS6xd8_DBBzrFpmgVw2J_k&sz=w2000",
    "date": "2026-05-10T22:41:12.101Z",
    "title": "DSC00474.JPG",
    "text": "Recuerdo de Copito 🤍"
  },
  {
    "name": "DSC00778.JPG",
    "url": "https://drive.google.com/thumbnail?id=1GwM-DhddY2S5jt3lN2qxl0JKZUm1Oqmg&sz=w2000",
    "date": "2026-05-10T22:41:12.946Z",
    "title": "DSC00778.JPG",
    "text": "Recuerdo de Copito 🤍"
  },
  {
    "name": "IMG-20141029-WA0000.jpg",
    "url": "https://drive.google.com/thumbnail?id=1-KqeFAKUwI_lnGV6LVUI3f78oCdXnia0&sz=w2000",
    "date": "2026-05-10T22:41:28.467Z",
    "title": "IMG-20141029-WA0000.jpg",
    "text": "Recuerdo de Copito 🤍"
  },
  {
    "name": "SA400273.JPG",
    "url": "https://drive.google.com/thumbnail?id=13OCRubSLMZJNcNA59YcJ1RGXV4k-TqDF&sz=w2000",
    "date": "2026-05-10T22:41:30.263Z",
    "title": "SA400273.JPG",
    "text": "Recuerdo de Copito 🤍"
  },
  {
    "name": "IMG_20170303_215708(1).jpg",
    "url": "https://drive.google.com/thumbnail?id=12MUnVJ6X6kV8QrjPW2iZX_1xgv2C6nJU&sz=w2000",
    "date": "2026-05-10T22:41:21.241Z",
    "title": "IMG_20170303_215708(1).jpg",
    "text": "Recuerdo de Copito 🤍"
  },
  {
    "name": "DSC00608.JPG",
    "url": "https://drive.google.com/thumbnail?id=1qabXlPGsDK_uwJv1kMUjbWq3jKmEmn4e&sz=w2000",
    "date": "2026-05-10T22:51:29.933Z",
    "title": "DSC00608.JPG",
    "text": "Recuerdo de Copito 🤍"
  },
  {
    "name": "IMG_20211127_193955.jpg",
    "url": "https://drive.google.com/thumbnail?id=1hg6X2NgMEdsvFO6OjkIRrwcyx3msESKE&sz=w2000",
    "date": "2026-05-10T22:52:52.031Z",
    "title": "IMG_20211127_193955.jpg",
    "text": "Recuerdo de Copito 🤍"
  },
  {
    "name": "IMG_20170206_224246.jpg",
    "url": "https://drive.google.com/thumbnail?id=1dY11KO7wLJJD8_BNn-Cq9MUobKe9Cyr1&sz=w2000",
    "date": "2026-05-10T22:41:23.777Z",
    "title": "IMG_20170206_224246.jpg",
    "text": "Recuerdo de Copito 🤍"
  },
  {
    "name": "IMG_20210514_151828.jpg",
    "url": "https://drive.google.com/thumbnail?id=1dobddtOyuH80pyIwoHNqOppbv8Ggu5na&sz=w2000",
    "date": "2026-05-10T22:52:45.718Z",
    "title": "IMG_20210514_151828.jpg",
    "text": "Recuerdo de Copito 🤍"
  },
  {
    "name": "IMG_20170206_224237.jpg",
    "url": "https://drive.google.com/thumbnail?id=1ruBdowG0Xc4s-zWaGq3nRtJLNAZj8hDy&sz=w2000",
    "date": "2026-05-10T22:41:23.391Z",
    "title": "IMG_20170206_224237.jpg",
    "text": "Recuerdo de Copito 🤍"
  }
]
